{
  "id": 3501,
  "lines": [
    {
      "id": 4501,
      "account_number": "4000",
      "account_name": "4000 - Sales",
      "department_name": "Acme Division B",
      "tags": [],
      "description": "Fabricated — user tenant had no real debit memos at capture time. Structure follows the credit-memo shape since the SDK types both with similar field sets.",
      "amount": 250,
      "tax": 0,
      "created_at": "2025-01-01T00:00:00+0000",
      "last_modified_at": "2025-01-01T00:00:00+0000",
      "account": 620,
      "tax_rate": null,
      "department": 4003
    }
  ],
  "payments": [],
  "amount_remaining": 250,
  "entity_name": "Acme Corp (US)",
  "entity_currency": "USD",
  "vendor_name": "Gamma LLC",
  "vendor_email": "ap@gamma.example",
  "debit_account_name": "2000 - Accounts Payable",
  "attachments": [],
  "debit_memo_number": "DN-TEST-0001",
  "voided_date": null,
  "is_deleted": false,
  "deleted_at": null,
  "search_vector": "'fake':1A",
  "search_text": " DN_TEST_0001 Gamma LLC",
  "debit_memo_type": "debit_memo",
  "ref_number": null,
  "debit_memo_date": "2026-01-20",
  "applied_date": null,
  "message_on_debit_memo": null,
  "application_status": "open",
  "currency": "USD",
  "exchange_rate": 1,
  "exchange_rate_book": 1,
  "created_at": "2025-01-01T00:00:00+0000",
  "last_sent_at": null,
  "anrok_transaction_id": null,
  "integration_id": null,
  "integration_context": null,
  "vat_number": null,
  "total_amount": 250,
  "amount_used": 0,
  "chat_id": null,
  "entity": 101,
  "vendor": 770,
  "debit_account": 602,
  "journal_entry": 9504,
  "voided_journal_entry": null,
  "total_amount_book": "250.00",
  "amount_used_book": "0.00",
  "total_amount_consolidation": "250.00",
  "amount_used_consolidation": "0.00"
}
